{
	"mesh":{
		"type":"asfem",
		"dim":2,
		"nx":20,
		"ny":20,
		"xmax":5.0,
		"ymax":5.0,
		"meshtype":"quad9",
		"savemesh":true
	},
	"dofs":{
		"names":["ux","uy"]
	},
	"elements":{
		"elmt1":{
			"type":"mechanics",
			"dofs":["ux","uy"],
			"material":{
				"type":"linearelastic",
				"parameters":{
					"E":1.0e3,
					"nu":0.3
				}
			}
		}
	},
	"projection":{
		"type":"default",
		"scalarmate":["vonMises-stress","vonMises-strain","hydrostatic-stress"],
		"rank2mate":["stress","strain"]
	},
	"nlsolver":{
		"type":"newton",
		"solver":"gmres",
		"maxiters":50,
		"abs-tolerance":5.0e-7,
		"rel-tolerance":5.0e-10,
		"s-tolerance":0.0,
		"preconditioner":"lu"
	},
	"output":{
		"type":"vtu",
		"interval":1
	},
	"bcs":{
		"fix":{
			"type":"dirichlet",
			"dofs":["ux","uy"],
			"bcvalue":0.0,
			"side":["bottom"]
		},
		"load":{
			"type":"dirichlet",
			"dofs":["uy"],
			"bcvalue":0.1,
			"side":["top"]
		}
	},
	"qpoints":{
		"bulk":{
			"type":"gauss-legendre",
			"order":4
		}
	},
	"job":{
		"type":"static",
		"print":"dep",
		"restart":true
	}
}